[{"InvType":"SALES","InvNo":"C33IN2000334","OnDate":"2020-12-31T00:00:00","BrandName":"Arvind Store","ProductName":"Suiting/Tresca/Poly Visc","Barcode":"T180021230","HSNCode":"55151190","Qty":1.2,"MRP":1872,"disc":0,"basic":1782.86,"Tax":89.14,"SAmt":44.57,"CAmt":44.57,"LineTotal":1872,"RoundOff":0,"BillAmt":0,"PaymentMode":"","SalesManName":"Mukesh Kumar","LP":"N","Tailoring":"N"},{"InvType":"SALES","InvNo":"C33IN2000334","OnDate":"2020-12-31T00:00:00","BrandName":"Arvind Store","ProductName":"Suiting/Tresca/Poly Visc","Barcode":"M67585901009","HSNCode":"54078230","Qty":1.2,"MRP":1047.6,"disc":0,"basic":997.72,"Tax":49.88,"SAmt":24.94,"CAmt":24.94,"LineTotal":1047.6,"RoundOff":0,"BillAmt":0,"PaymentMode":"","SalesManName":"Mukesh Kumar","LP":"N","Tailoring":"N"},{"InvType":"SALES","InvNo":"C33IN2000334","OnDate":"2020-12-31T00:00:00","BrandName":"Arvind Store","ProductName":"Suiting/Tresca/Poly Visc","Barcode":"M67586901011","HSNCode":"54078230","Qty":1.2,"MRP":1047.6,"disc":0,"basic":997.72,"Tax":49.88,"SAmt":24.94,"CAmt":24.94,"LineTotal":1047.6,"RoundOff":-0.2,"BillAmt":3967,"PaymentMode":"CRD","SalesManName":"Mukesh Kumar","LP":"N","Tailoring":"N"}]