[{"InvType":"SALES","InvNo":"C33IN1900777","OnDate":"2019-10-19T00:00:00","BrandName":"Arvind Store","ProductName":"Suiting/Tresca/Poly Wool","Barcode":"T180026402","HSNCode":"55151390","Qty":1.2,"MRP":1635.6,"disc":0,"basic":1557.72,"Tax":77.88,"SAmt":38.94,"CAmt":38.94,"LineTotal":1635.6,"RoundOff":0,"BillAmt":0,"PaymentMode":"","SalesManName":"Mukesh Kumar","LP":"Y","Tailoring":"N"},{"InvType":"SALES","InvNo":"C33IN1900777","OnDate":"2019-10-19T00:00:00","BrandName":"Arvind Store","ProductName":"Shirting/Non Tresca/Cotton","Barcode":"M46253401068","HSNCode":"","Qty":1.3,"MRP":1016.6,"disc":0,"basic":968.2,"Tax":48.4,"SAmt":24.2,"CAmt":24.2,"LineTotal":1016.6,"RoundOff":-0.2,"BillAmt":2652,"PaymentMode":"CRD","SalesManName":"Mukesh Kumar","LP":"Y","Tailoring":"N"}]