[{"InvType":"SALES","InvNo":"C33IN1700498","OnDate":"2017-11-17T00:00:00","BrandName":"Arvind Store","ProductName":"Shirting/Tresca/Cotton","Barcode":"M20405501007","HSNCode":"","Qty":2.6,"MRP":2917.2,"disc":0,"basic":2778.28,"Tax":138.92,"SAmt":69.46,"CAmt":69.46,"LineTotal":2917.2,"RoundOff":0,"BillAmt":0,"PaymentMode":"","SalesManName":"Mukesh Kumar","LP":"N","Tailoring":"N"},{"InvType":"SALES","InvNo":"C33IN1700498","OnDate":"2017-11-17T00:00:00","BrandName":"Arvind Store","ProductName":"Suiting/Tresca/Poly Wool","Barcode":"M46276101086","HSNCode":"","Qty":1.6,"MRP":2747.2,"disc":0,"basic":2616.38,"Tax":130.82,"SAmt":65.41,"CAmt":65.41,"LineTotal":2747.2,"RoundOff":-0.4,"BillAmt":5664,"PaymentMode":"CAS","SalesManName":"Mukesh Kumar","LP":"N","Tailoring":"N"}]