[{"InvType":"SALES","InvNo":"C33IN1700389","OnDate":"2017-09-28T00:00:00","BrandName":"Flying Machine","ProductName":"Apparel/Mens Casual/Jeans","Barcode":"8907378839152","HSNCode":"610342","Qty":1,"MRP":2699,"disc":674.75,"basic":2024.25,"Tax":242.92,"SAmt":121.46,"CAmt":121.46,"LineTotal":2267.17,"RoundOff":0,"BillAmt":0,"PaymentMode":"","SalesManName":"Mukesh Kumar","LP":"N","Tailoring":"N"},{"InvType":"SALES","InvNo":"C33IN1700389","OnDate":"2017-09-28T00:00:00","BrandName":"Arrow","ProductName":"Apparel/Mens Formal/Shirts","Barcode":"8907378501394","HSNCode":"620520","Qty":1,"MRP":2399,"disc":599.75,"basic":1799.25,"Tax":215.92,"SAmt":107.96,"CAmt":107.96,"LineTotal":2015.17,"RoundOff":0.32,"BillAmt":8817,"PaymentMode":"CRD","SalesManName":"Mukesh Kumar","LP":"N","Tailoring":"N"},{"InvType":"SALES","InvNo":"C33IN1700389","OnDate":"2017-09-28T00:00:00","BrandName":"Flying Machine","ProductName":"Apparel/Mens Casual/Jeans","Barcode":"8907378842077","HSNCode":"610342","Qty":1,"MRP":2999,"disc":749.75,"basic":2249.25,"Tax":269.92,"SAmt":134.96,"CAmt":134.96,"LineTotal":2519.17,"RoundOff":0,"BillAmt":0,"PaymentMode":"","SalesManName":"Mukesh Kumar","LP":"N","Tailoring":"N"},{"InvType":"SALES","InvNo":"C33IN1700389","OnDate":"2017-09-28T00:00:00","BrandName":"US Polo Association","ProductName":"Apparel/Mens Casual/Jeans","Barcode":"8903952887007","HSNCode":"610342","Qty":1,"MRP":2399,"disc":599.75,"basic":1799.25,"Tax":215.92,"SAmt":107.96,"CAmt":107.96,"LineTotal":2015.17,"RoundOff":0,"BillAmt":0,"PaymentMode":"","SalesManName":"Mukesh Kumar","LP":"N","Tailoring":"N"}]