[{"InvType":"SALES","InvNo":"C33IN2000407","OnDate":"2021-03-01T00:00:00","BrandName":"Arvind Store","ProductName":"Shirting/Tresca/Cot Modal","Barcode":"M54861901013","HSNCode":"52121400","Qty":1.7,"MRP":1630.3,"disc":163.03,"basic":1397.4,"Tax":69.88,"SAmt":34.94,"CAmt":34.94,"LineTotal":1467.28,"RoundOff":0,"BillAmt":0,"PaymentMode":"","SalesManName":"Sanjeev Kumar Mishra","LP":"N","Tailoring":"N"},{"InvType":"SALES","InvNo":"C33IN2000407","OnDate":"2021-03-01T00:00:00","BrandName":"Arvind Store","ProductName":"Shirting/Tresca/Cotton","Barcode":"R200378423","HSNCode":"52084320","Qty":1.7,"MRP":1463.7,"disc":146.37,"basic":1254.6,"Tax":62.74,"SAmt":31.37,"CAmt":31.37,"LineTotal":1317.34,"RoundOff":0,"BillAmt":0,"PaymentMode":"","SalesManName":"Sanjeev Kumar Mishra","LP":"N","Tailoring":"N"},{"InvType":"SALES","InvNo":"C33IN2000407","OnDate":"2021-03-01T00:00:00","BrandName":"Arvind Store","ProductName":"Suiting/Tresca/Poly Wool","Barcode":"R200420286","HSNCode":"55151390","Qty":1.3,"MRP":1908.4,"disc":190.84,"basic":1635.77,"Tax":81.78,"SAmt":40.89,"CAmt":40.89,"LineTotal":1717.55,"RoundOff":0,"BillAmt":0,"PaymentMode":"","SalesManName":"Sanjeev Kumar Mishra","LP":"N","Tailoring":"N"},{"InvType":"SALES","InvNo":"C33IN2000407","OnDate":"2021-03-01T00:00:00","BrandName":"Arvind Store","ProductName":"Suiting/Tresca/Poly Wool","Barcode":"R200454541","HSNCode":"55151190","Qty":1.3,"MRP":1498.9,"disc":149.89,"basic":1284.77,"Tax":64.24,"SAmt":32.12,"CAmt":32.12,"LineTotal":1349.01,"RoundOff":-0.18,"BillAmt":5851,"PaymentMode":"CAS","SalesManName":"Sanjeev Kumar Mishra","LP":"N","Tailoring":"N"}]