[{"InvType":"SALES","InvNo":"C33IN2000451","OnDate":"2021-03-12T00:00:00","BrandName":"US Polo Association","ProductName":"Apparel/Mens Casual/T shirts","Barcode":"8907686780986","HSNCode":"","Qty":1,"MRP":1799,"disc":899.5,"basic":856.67,"Tax":42.84,"SAmt":21.42,"CAmt":21.42,"LineTotal":899.51,"RoundOff":0,"BillAmt":1499,"PaymentMode":"CAS","SalesManName":"Mukesh Kumar","LP":"N","Tailoring":"N"},{"InvType":"SALES","InvNo":"C33IN2000451","OnDate":"2021-03-12T00:00:00","BrandName":"US Polo Association","ProductName":"Apparel/Mens Casual/T shirts","Barcode":"8907686787534","HSNCode":"610910","Qty":1,"MRP":1199,"disc":599.5,"basic":570.95,"Tax":28.54,"SAmt":14.27,"CAmt":14.27,"LineTotal":599.49,"RoundOff":0,"BillAmt":0,"PaymentMode":"","SalesManName":"Mukesh Kumar","LP":"N","Tailoring":"N"}]