[{"InvType":"SALES","InvNo":"C33IN1800428","OnDate":"2018-06-21T00:00:00","BrandName":"Arvind Store","ProductName":"Shirting/Non Tresca/Cotton","Barcode":"M37485501018","HSNCode":"","Qty":1.6,"MRP":990.4,"disc":0,"basic":943.24,"Tax":47.16,"SAmt":23.58,"CAmt":23.58,"LineTotal":990.4,"RoundOff":0,"BillAmt":0,"PaymentMode":"","SalesManName":"Mukesh Kumar","LP":"Y","Tailoring":"N"},{"InvType":"SALES","InvNo":"C33IN1800428","OnDate":"2018-06-21T00:00:00","BrandName":"Arvind Store","ProductName":"Shirting/Non Tresca/Cotton","Barcode":"M66041001041","HSNCode":"52083290","Qty":1.6,"MRP":897.6,"disc":0,"basic":854.86,"Tax":42.74,"SAmt":21.37,"CAmt":21.37,"LineTotal":897.6,"RoundOff":-0.2,"BillAmt":4051,"PaymentMode":"CAS","SalesManName":"Mukesh Kumar","LP":"Y","Tailoring":"N"},{"InvType":"SALES","InvNo":"C33IN1800428","OnDate":"2018-06-21T00:00:00","BrandName":"Arvind Store","ProductName":"Shirting/Non Tresca/Cotton","Barcode":"M56172901049","HSNCode":"52082290","Qty":3.2,"MRP":2163.2,"disc":0,"basic":2060.2,"Tax":103,"SAmt":51.5,"CAmt":51.5,"LineTotal":2163.2,"RoundOff":0,"BillAmt":0,"PaymentMode":"","SalesManName":"Mukesh Kumar","LP":"Y","Tailoring":"N"}]