[{"InvType":"SALES","InvNo":"C33IN1800091","OnDate":"2018-04-17T00:00:00","BrandName":"Arvind Store","ProductName":"Shirting/Non Tresca/Cotton","Barcode":"MTS000000007I","HSNCode":"52082180","Qty":1.6,"MRP":248,"disc":49.6,"basic":188.95,"Tax":9.44,"SAmt":4.72,"CAmt":4.72,"LineTotal":198.39,"RoundOff":0.36,"BillAmt":4449,"PaymentMode":"CAS","SalesManName":"Santosh Kumar","LP":"N","Tailoring":"N"},{"InvType":"SALES","InvNo":"C33IN1800091","OnDate":"2018-04-17T00:00:00","BrandName":"Arvind Store","ProductName":"Suiting/Tresca/Poly Wool","Barcode":"M45157101025","HSNCode":"","Qty":1.2,"MRP":1938,"disc":387.6,"basic":1476.57,"Tax":73.82,"SAmt":36.91,"CAmt":36.91,"LineTotal":1550.39,"RoundOff":0,"BillAmt":0,"PaymentMode":"","SalesManName":"Santosh Kumar","LP":"N","Tailoring":"N"},{"InvType":"SALES","InvNo":"C33IN1800091","OnDate":"2018-04-17T00:00:00","BrandName":"Arvind Store","ProductName":"Shirting/Non Tresca/Cotton","Barcode":"M47488601063","HSNCode":"","Qty":2,"MRP":1306,"disc":261.2,"basic":995.05,"Tax":49.76,"SAmt":24.88,"CAmt":24.88,"LineTotal":1044.81,"RoundOff":0,"BillAmt":0,"PaymentMode":"","SalesManName":"Santosh Kumar","LP":"N","Tailoring":"N"},{"InvType":"SALES","InvNo":"C33IN1800091","OnDate":"2018-04-17T00:00:00","BrandName":"Arvind Store","ProductName":"Shirting/Tresca/Linen","Barcode":"M44290301015","HSNCode":"","Qty":1.6,"MRP":2068.8,"disc":413.76,"basic":1576.23,"Tax":78.82,"SAmt":39.41,"CAmt":39.41,"LineTotal":1655.05,"RoundOff":0,"BillAmt":0,"PaymentMode":"","SalesManName":"Santosh Kumar","LP":"N","Tailoring":"N"}]