[{"InvType":"SALES","InvNo":"C33IN1801189","OnDate":"2019-01-26T00:00:00","BrandName":"Arvind Store","ProductName":"Shirting/Tresca/Cotton","Barcode":"M68725801013","HSNCode":"52084320","Qty":1.6,"MRP":1508.8,"disc":301.76,"basic":1149.56,"Tax":57.48,"SAmt":28.74,"CAmt":28.74,"LineTotal":1207.04,"RoundOff":-0.05,"BillAmt":10651,"PaymentMode":"CAS","SalesManName":"Sanjeev Kumar Mishra","LP":"N","Tailoring":"N"},{"InvType":"SALES","InvNo":"C33IN1801189","OnDate":"2019-01-26T00:00:00","BrandName":"Arvind Store","ProductName":"Suiting/Tresca/Poly Wool","Barcode":"M51271301108","HSNCode":"55151390","Qty":3,"MRP":11805,"disc":2361,"basic":8994.29,"Tax":449.72,"SAmt":224.86,"CAmt":224.86,"LineTotal":9444.01,"RoundOff":0,"BillAmt":0,"PaymentMode":"","SalesManName":"Sanjeev Kumar Mishra","LP":"N","Tailoring":"N"}]