[{"InvType":"SALES","InvNo":"C33IN1800826","OnDate":"2018-10-12T00:00:00","BrandName":"Flying Machine","ProductName":"Apparel/Mens Casual/T shirts","Barcode":"8907686276922","HSNCode":"610910","Qty":1,"MRP":799,"disc":0,"basic":760.96,"Tax":38.04,"SAmt":19.02,"CAmt":19.02,"LineTotal":799,"RoundOff":0,"BillAmt":0,"PaymentMode":"","SalesManName":"Santosh Kumar","LP":"Y","Tailoring":"N"},{"InvType":"SALES","InvNo":"C33IN1800826","OnDate":"2018-10-12T00:00:00","BrandName":"Flying Machine","ProductName":"Apparel/Mens Casual/T shirts","Barcode":"8907686275000","HSNCode":"610910","Qty":1,"MRP":799,"disc":0,"basic":760.96,"Tax":38.04,"SAmt":19.02,"CAmt":19.02,"LineTotal":799,"RoundOff":0,"BillAmt":1598,"PaymentMode":"CAS","SalesManName":"Santosh Kumar","LP":"Y","Tailoring":"N"}]