[{"InvType":"SALES","InvNo":"C33IN500186","OnDate":"2016-03-25T00:00:00","BrandName":"US Polo Association","ProductName":"Apparel/Mens Formal/Shirts","Barcode":"8907259144108","HSNCode":"","Qty":1,"MRP":1999,"disc":0,"basic":1903.81,"Tax":0,"SAmt":95.19,"CAmt":0,"LineTotal":0,"RoundOff":0,"BillAmt":0,"PaymentMode":"","SalesManName":"Bikas Kumar Sah","LP":"N","Tailoring":""},{"InvType":"SALES","InvNo":"C33IN500186","OnDate":"2016-03-25T00:00:00","BrandName":"Hanes International","ProductName":"Apparel/Accessories/Socks","Barcode":"8907036298710","HSNCode":"","Qty":1,"MRP":299,"disc":0,"basic":284.76,"Tax":0,"SAmt":14.24,"CAmt":0,"LineTotal":0,"RoundOff":0,"BillAmt":0,"PaymentMode":"","SalesManName":"Bikas Kumar Sah","LP":"N","Tailoring":""},{"InvType":"SALES","InvNo":"C33IN500186","OnDate":"2016-03-25T00:00:00","BrandName":"US Polo Association","ProductName":"Apparel/Mens Formal/Trousers","Barcode":"8907259224619","HSNCode":"","Qty":1,"MRP":2499,"disc":0,"basic":2380,"Tax":0,"SAmt":119,"CAmt":0,"LineTotal":0,"RoundOff":0,"BillAmt":4797,"PaymentMode":"CAS","SalesManName":"Bikas Kumar Sah","LP":"N","Tailoring":""}]