[{"InvType":"SALES","InvNo":"C33IN1900477","OnDate":"2019-07-27T00:00:00","BrandName":"Flying Machine","ProductName":"Apparel/Mens Casual/T shirts","Barcode":"8907686276656","HSNCode":"610910","Qty":1,"MRP":799,"disc":0,"basic":760.96,"Tax":38.04,"SAmt":19.02,"CAmt":19.02,"LineTotal":799,"RoundOff":0,"BillAmt":799,"PaymentMode":"CAS","SalesManName":"Santosh Kumar","LP":"Y","Tailoring":"N"},{"InvType":"SALES","InvNo":"C33IN1900477","OnDate":"2019-07-27T00:00:00","BrandName":"Flying Machine","ProductName":"Apparel/Mens Casual/T shirts","Barcode":"8907686139579","HSNCode":"610510","Qty":1,"MRP":799,"disc":799,"basic":0,"Tax":0,"SAmt":0,"CAmt":0,"LineTotal":0,"RoundOff":0,"BillAmt":0,"PaymentMode":"","SalesManName":"Santosh Kumar","LP":"Y","Tailoring":"N"}]