[{"InvType":"SALES","InvNo":"C33IN1800821","OnDate":"2018-10-11T00:00:00","BrandName":"Arvind Store","ProductName":"Suiting/Tresca/Poly Wool","Barcode":"M43441401040","HSNCode":"","Qty":1.2,"MRP":1672.8,"disc":0,"basic":1593.14,"Tax":79.66,"SAmt":39.83,"CAmt":39.83,"LineTotal":1672.8,"RoundOff":0.4,"BillAmt":4738,"PaymentMode":"CAS","SalesManName":"Mukesh Kumar","LP":"Y","Tailoring":"N"},{"InvType":"SALES","InvNo":"C33IN1800821","OnDate":"2018-10-11T00:00:00","BrandName":"Arvind Store","ProductName":"Suiting/Tresca/Poly Wool","Barcode":"M59854901006","HSNCode":"55151390","Qty":1.2,"MRP":1509.6,"disc":0,"basic":1437.72,"Tax":71.88,"SAmt":35.94,"CAmt":35.94,"LineTotal":1509.6,"RoundOff":0,"BillAmt":0,"PaymentMode":"","SalesManName":"Mukesh Kumar","LP":"Y","Tailoring":"N"},{"InvType":"SALES","InvNo":"C33IN1800821","OnDate":"2018-10-11T00:00:00","BrandName":"Arvind Store","ProductName":"Shirting/Tresca/Cotton","Barcode":"M34320001014","HSNCode":"","Qty":1.6,"MRP":1555.2,"disc":0,"basic":1481.14,"Tax":74.06,"SAmt":37.03,"CAmt":37.03,"LineTotal":1555.2,"RoundOff":0,"BillAmt":0,"PaymentMode":"","SalesManName":"Mukesh Kumar","LP":"Y","Tailoring":"N"}]