[{"InvType":"SALES","InvNo":"C33IN1700420","OnDate":"2017-10-16T00:00:00","BrandName":"US Polo Association","ProductName":"Apparel/Mens Formal/Shirts","Barcode":"8907538599377","HSNCode":"620530","Qty":1,"MRP":2099,"disc":0,"basic":1874.1,"Tax":224.9,"SAmt":112.45,"CAmt":112.45,"LineTotal":2099,"RoundOff":0,"BillAmt":0,"PaymentMode":"","SalesManName":"Sanjeev Kumar Mishra","LP":"N","Tailoring":"N"},{"InvType":"SALES","InvNo":"C33IN1700420","OnDate":"2017-10-16T00:00:00","BrandName":"Arvind Store","ProductName":"Shirting/Tresca/Cotton","Barcode":"M56881401013","HSNCode":"52083290","Qty":1.6,"MRP":1745.6,"disc":0,"basic":1662.48,"Tax":83.12,"SAmt":41.56,"CAmt":41.56,"LineTotal":1745.6,"RoundOff":0.4,"BillAmt":7144,"PaymentMode":"CAS","SalesManName":"Sanjeev Kumar Mishra","LP":"N","Tailoring":"N"},{"InvType":"SALES","InvNo":"C33IN1700420","OnDate":"2017-10-16T00:00:00","BrandName":"US Polo Association","ProductName":"Apparel/Mens Casual/Jeans","Barcode":"8907538563309","HSNCode":"610342","Qty":1,"MRP":3299,"disc":0,"basic":2945.54,"Tax":353.46,"SAmt":176.73,"CAmt":176.73,"LineTotal":3299,"RoundOff":0,"BillAmt":0,"PaymentMode":"","SalesManName":"Sanjeev Kumar Mishra","LP":"N","Tailoring":"N"}]