[{"InvType":"SALES","InvNo":"C33IN500144","OnDate":"2016-03-12T00:00:00","BrandName":"Arvind Store","ProductName":"Shirting/Tresca/Cotton","Barcode":"M40501501013","HSNCode":"","Qty":1.7,"MRP":1290.3,"disc":0,"basic":1290.3,"Tax":0,"SAmt":0,"CAmt":0,"LineTotal":0,"RoundOff":0.3,"BillAmt":3215,"PaymentMode":"CAS","SalesManName":"Bikas Kumar Sah","LP":"N","Tailoring":""},{"InvType":"SALES","InvNo":"C33IN500144","OnDate":"2016-03-12T00:00:00","BrandName":"Arvind Store","ProductName":"Shirting/Non Tresca/Cotton","Barcode":"M35878501115","HSNCode":"","Qty":1.7,"MRP":938.4,"disc":0,"basic":938.4,"Tax":0,"SAmt":0,"CAmt":0,"LineTotal":0,"RoundOff":0,"BillAmt":0,"PaymentMode":"","SalesManName":"Bikas Kumar Sah","LP":"N","Tailoring":""},{"InvType":"SALES","InvNo":"C33IN500144","OnDate":"2016-03-12T00:00:00","BrandName":"Arvind Store","ProductName":"Shirting/Non Tresca/Cotton","Barcode":"M35045101031","HSNCode":"","Qty":1.7,"MRP":986,"disc":0,"basic":986,"Tax":0,"SAmt":0,"CAmt":0,"LineTotal":0,"RoundOff":0,"BillAmt":0,"PaymentMode":"","SalesManName":"Bikas Kumar Sah","LP":"N","Tailoring":""}]