[{"InvType":"SALES","InvNo":"C33IN600202","OnDate":"2016-05-11T00:00:00","BrandName":"Arvind Store","ProductName":"Shirting/Tresca/Linen","Barcode":"M39222301001","HSNCode":"","Qty":1.6,"MRP":2104,"disc":0,"basic":2104,"Tax":0,"SAmt":0,"CAmt":0,"LineTotal":0,"RoundOff":0,"BillAmt":0,"PaymentMode":"","SalesManName":"Mukesh Kumar","LP":"N","Tailoring":""},{"InvType":"SALES","InvNo":"C33IN600202","OnDate":"2016-05-11T00:00:00","BrandName":"Arvind Store","ProductName":"Shirting/Non Tresca/Cotton","Barcode":"M38457301023","HSNCode":"","Qty":1.6,"MRP":982.4,"disc":0,"basic":982.4,"Tax":0,"SAmt":0,"CAmt":0,"LineTotal":0,"RoundOff":-0.4,"BillAmt":3086,"PaymentMode":"CRD","SalesManName":"Mukesh Kumar","LP":"N","Tailoring":""}]