[{"InvType":"SALES","InvNo":"C33IN2000050","OnDate":"2020-08-29T00:00:00","BrandName":"Arvind Store","ProductName":"Shirting/Tresca/Cotton","Barcode":"M56452501007","HSNCode":"52084320","Qty":1.7,"MRP":4828,"disc":0,"basic":4598.1,"Tax":229.9,"SAmt":114.95,"CAmt":114.95,"LineTotal":4828,"RoundOff":0,"BillAmt":0,"PaymentMode":"","SalesManName":"Mukesh Kumar","LP":"Y","Tailoring":"N"},{"InvType":"SALES","InvNo":"C33IN2000050","OnDate":"2020-08-29T00:00:00","BrandName":"Arvind Store","ProductName":"Shirting/Tresca/Cotton","Barcode":"M64090601016","HSNCode":"52082390","Qty":1.7,"MRP":4020.5,"disc":0,"basic":3829.04,"Tax":191.46,"SAmt":95.73,"CAmt":95.73,"LineTotal":4020.5,"RoundOff":0.5,"BillAmt":12827,"PaymentMode":"CAS","SalesManName":"Mukesh Kumar","LP":"Y","Tailoring":"N"},{"InvType":"SALES","InvNo":"C33IN2000050","OnDate":"2020-08-29T00:00:00","BrandName":"Arvind Store","ProductName":"Suiting/Tresca/Poly Wool","Barcode":"T180007002","HSNCode":"55163300","Qty":1.3,"MRP":3978,"disc":0,"basic":3788.58,"Tax":189.42,"SAmt":94.71,"CAmt":94.71,"LineTotal":3978,"RoundOff":0,"BillAmt":0,"PaymentMode":"","SalesManName":"Mukesh Kumar","LP":"Y","Tailoring":"N"}]