[{"InvType":"SALES","InvNo":"C33IN1800545","OnDate":"2018-07-28T00:00:00","BrandName":"Arvind Store","ProductName":"Shirting/Tresca/Linen","Barcode":"M60486101031","HSNCode":"53092990","Qty":1.5,"MRP":942,"disc":0,"basic":897.14,"Tax":44.86,"SAmt":22.43,"CAmt":22.43,"LineTotal":942,"RoundOff":0,"BillAmt":0,"PaymentMode":"","SalesManName":"Santosh Kumar","LP":"Y","Tailoring":"N"},{"InvType":"SALES","InvNo":"C33IN1800545","OnDate":"2018-07-28T00:00:00","BrandName":"Arvind Store","ProductName":"Shirting/Non Tresca/Cotton","Barcode":"M37485201020","HSNCode":"","Qty":1.5,"MRP":852,"disc":0,"basic":811.42,"Tax":40.58,"SAmt":20.29,"CAmt":20.29,"LineTotal":852,"RoundOff":0,"BillAmt":0,"PaymentMode":"","SalesManName":"Santosh Kumar","LP":"Y","Tailoring":"N"},{"InvType":"SALES","InvNo":"C33IN1800545","OnDate":"2018-07-28T00:00:00","BrandName":"Arvind Store","ProductName":"Shirting/Tresca/Cotton","Barcode":"M60452801003","HSNCode":"52083390","Qty":1.4,"MRP":1106,"disc":0,"basic":1053.34,"Tax":52.66,"SAmt":26.33,"CAmt":26.33,"LineTotal":1106,"RoundOff":0,"BillAmt":2900,"PaymentMode":"CAS","SalesManName":"Santosh Kumar","LP":"Y","Tailoring":"N"}]