[{"InvType":"SALES","InvNo":"C33IN1700474","OnDate":"2017-11-08T00:00:00","BrandName":"Flying Machine","ProductName":"Apparel/Mens Casual/Jeans","Barcode":"8907538539106","HSNCode":"610342","Qty":1,"MRP":2699,"disc":0,"basic":2375.12,"Tax":323.88,"SAmt":161.94,"CAmt":161.94,"LineTotal":2699,"RoundOff":0.2,"BillAmt":4933,"PaymentMode":"CAS","SalesManName":"Mukesh Kumar","LP":"N","Tailoring":"N"},{"InvType":"SALES","InvNo":"C33IN1700474","OnDate":"2017-11-08T00:00:00","BrandName":"Arvind Store","ProductName":"Shirting/Tresca/Linen","Barcode":"M46278401002","HSNCode":"","Qty":1.7,"MRP":2233.8,"disc":0,"basic":2127.42,"Tax":106.38,"SAmt":53.19,"CAmt":53.19,"LineTotal":2233.8,"RoundOff":0,"BillAmt":0,"PaymentMode":"","SalesManName":"Mukesh Kumar","LP":"N","Tailoring":"N"}]