[{"InvType":"SALES","InvNo":"C33IN1700089","OnDate":"2017-07-20T00:00:00","BrandName":"Arvind Store","ProductName":"Suiting/Tresca/Poly Wool","Barcode":"M43447501029","HSNCode":"","Qty":1.3,"MRP":3250,"disc":487.5,"basic":2762.5,"Tax":138.12,"SAmt":69.06,"CAmt":69.06,"LineTotal":2900.62,"RoundOff":-0.37,"BillAmt":4733,"PaymentMode":"CAS","SalesManName":"Santosh Kumar","LP":"N","Tailoring":"N"},{"InvType":"SALES","InvNo":"C33IN1700089","OnDate":"2017-07-20T00:00:00","BrandName":"Arvind Store","ProductName":"Shirting/Non Tresca/Linen","Barcode":"M29158401098","HSNCode":"","Qty":1.5,"MRP":2053.5,"disc":308.02,"basic":1745.47,"Tax":87.28,"SAmt":43.64,"CAmt":43.64,"LineTotal":1832.75,"RoundOff":0,"BillAmt":0,"PaymentMode":"","SalesManName":"Santosh Kumar","LP":"N","Tailoring":"N"}]